{"chunk_definitions":[{"row":7,"row_count":1,"visible":true,"expansion_state":0,"options":{"engine":"r","label":"unnamed-chunk-1"},"document_id":"7097F0A3","chunk_id":"cho5rock5cdid","chunk_label":"unnamed-chunk-1"},{"row":17,"row_count":1,"visible":true,"expansion_state":0,"options":{"engine":"r","label":"unnamed-chunk-2"},"document_id":"7097F0A3","chunk_id":"cay3es3ywkjfl","chunk_label":"unnamed-chunk-2"},{"row":35,"row_count":1,"visible":true,"expansion_state":0,"options":{"engine":"r","label":"unnamed-chunk-3"},"document_id":"7097F0A3","chunk_id":"ctm1zlj5wvsd5","chunk_label":"unnamed-chunk-3"},{"row":44,"row_count":1,"visible":true,"expansion_state":0,"options":{"engine":"r","label":"unnamed-chunk-4"},"document_id":"7097F0A3","chunk_id":"c2xj314hawnit","chunk_label":"unnamed-chunk-4"},{"row":54,"row_count":1,"visible":true,"expansion_state":0,"options":{"engine":"r","label":"unnamed-chunk-5"},"document_id":"7097F0A3","chunk_id":"ck81z494ko5n6","chunk_label":"unnamed-chunk-5"}],"doc_write_time":1717089404}